<package>
  <description brief="Common ROS Services">

    Service definitions that are common for different robots

  </description>
  <author>Morgan Quigley/mquigley@cs.stanford.edu</author>
  <license>BSD</license>
  <review status="unreviewed" notes=""/>
  <url>http://pr.willowgarage.com/wiki/robot_srvs</url>
  <logo>http://www.willowgarage.com/files/willowgarage/robot10.jpg</logo>
  <depend package="std_msgs"/>
  <depend package="robot_msgs"/>
  <depend package="nav_msgs"/><!-- will not be needed when StaticMap is moved to nav_srvs -->
  <export>
    <cpp cflags="-I${prefix}/srv/cpp"/>
  </export>
</package>

